{
 "arm": "production",
 "base_ref_oid": "8b99891c1057ffca76cefca75c4ff6f889c30116",
 "cost": 0.267555,
 "duration_s": 67.0,
 "duration_source": "log-mtime",
 "fidelity": "reconstructed",
 "head_sha": "4d408b7ea37922955fd248d1eb85ae3f57129176",
 "mode": "commit",
 "pr": 42,
 "ran": [
  "api-design"
 ],
 "repo": "FormalFrontier/TauCeti",
 "round": 8,
 "round_id": "42-8",
 "rubrics_version": "dccacfb6e0bf58e2",
 "run_ids": [
  "r-20260605T030934Z-42-api-design-66f6b7"
 ],
 "schema": "tauceti.round/v1",
 "scoreboard_blob": "e75a1c0e6e34376402f9a2d4131fb06b612ab5a97d3e8227729205b5602ffa70",
 "scoreboard_sha256": "e75a1c0e6e34376402f9a2d4131fb06b612ab5a97d3e8227729205b5602ffa70",
 "source": "backfill-ledger",
 "states": {
  "api-design": "blocking_request",
  "attribution": "stale",
  "correctness": "stale",
  "deprecation": "stale",
  "documentation": "stale",
  "generality": "stale",
  "naming": "stale",
  "placement": "stale",
  "proof-quality": "stale",
  "reuse": "stale",
  "scope": "stale"
 },
 "ts": "2026-06-05T03:09:34.498223+00:00"
}
