{
 "arm": "production",
 "base_ref_oid": "ffd46b4684b23372affece11c67881eb38c3cb90",
 "cost": 0.403329,
 "duration_s": 127.0,
 "duration_source": "log-mtime",
 "fidelity": "reconstructed",
 "head_sha": "432f65e4213c260c4662e2fe99d0773a5f350d7d",
 "mode": "commit",
 "pr": 118,
 "ran": [
  "reuse",
  "api-design",
  "placement"
 ],
 "repo": "FormalFrontier/TauCeti",
 "round": 3,
 "round_id": "118-3",
 "rubrics_version": "68ec685af806ec41",
 "run_ids": [
  "r-20260610T185818Z-118-reuse-aa500d",
  "r-20260610T185818Z-118-api-design-17233f",
  "r-20260610T185818Z-118-placement-f2d6fe"
 ],
 "schema": "tauceti.round/v1",
 "scoreboard_blob": "accf41cbe49c2c9003321b406ba1fcf76e255fcc2dc3794cd45c3f0b0ed62f27",
 "scoreboard_sha256": "accf41cbe49c2c9003321b406ba1fcf76e255fcc2dc3794cd45c3f0b0ed62f27",
 "source": "backfill-ledger",
 "states": {
  "api-design": "blocking_request",
  "attribution": "stale",
  "correctness": "stale",
  "deprecation": "stale",
  "documentation": "stale",
  "generality": "stale",
  "naming": "stale",
  "placement": "green",
  "proof-quality": "stale",
  "reuse": "green",
  "scope": "stale"
 },
 "ts": "2026-06-10T18:58:18.044308+00:00"
}
