{
 "head_sha": "86b3fd531a183e24d2978f22af2f08b9fbde7162",
 "posted_at": "2026-06-25T21:43:29.581408+00:00",
 "pr": 451,
 "repo": "FormalFrontier/TauCeti",
 "round": 2,
 "schema": "tauceti.post/v1",
 "scoreboard_body_sha256": "a7bbfac6f88ad098bdfc8f789cda286816bfa0dbd57f7e741387d9012d2c20f3",
 "scoreboard_comment_id": 4804338135,
 "threads": {
  "api-design": 3477813828,
  "attribution": 3477813749,
  "documentation": 3477814112,
  "generality": 3477813916,
  "naming": 3477814053,
  "placement": 3477813992
 }
}
