{
 "head_sha": "b4ebbadecf5a2daa31c5afe4eaa7c112732cfa17",
 "posted_at": "2026-06-23T16:23:34.012996+00:00",
 "pr": 342,
 "repo": "FormalFrontier/TauCeti",
 "round": 2,
 "schema": "tauceti.post/v1",
 "scoreboard_body_sha256": "6841a3c529d5bde9ef5b1b12683959ee2abbc59e30d9aaa9b0b07fe3346ef868",
 "scoreboard_comment_id": 4774171255,
 "threads": {
  "api-design": 3456690483,
  "api-design:reply": 3461284146,
  "generality": 3456690511,
  "naming": 3458704795,
  "proof-quality": 3458704889,
  "reuse": 3456690446
 }
}
