{
 "head_sha": "efcf3d19563f5dff221b2c2a283ac54fa62a24f9",
 "posted_at": "2026-06-26T17:51:28.523472+00:00",
 "pr": 475,
 "repo": "FormalFrontier/TauCeti",
 "round": 1,
 "schema": "tauceti.post/v1",
 "scoreboard_body_sha256": "fa34151a9bc9110d189e4669033862e868c3cb003824b089c7300e72de19796d",
 "scoreboard_comment_id": 4811597571,
 "threads": {
  "api-design": 3482863563,
  "api-design:reply": 3483171781,
  "documentation": 3483172111,
  "generality": 3482863638,
  "generality:reply": 3483171934,
  "placement": 3482863706,
  "placement:reply": 3483172050,
  "proof-quality": 3482863763,
  "proof-quality:reply": 3483172363,
  "reuse": 3482863494,
  "reuse:reply": 3483171644
 }
}
