{
 "failures": [
  {
   "action": "thread POST correctness",
   "error": "gh: Validation Failed (HTTP 422)\n"
  },
  {
   "action": "thread POST reuse",
   "error": "gh: Validation Failed (HTTP 422)\n"
  },
  {
   "action": "thread POST scope",
   "error": "gh: Validation Failed (HTTP 422)\n"
  },
  {
   "action": "thread POST attribution",
   "error": "gh: Validation Failed (HTTP 422)\n"
  },
  {
   "action": "thread POST api-design",
   "error": "gh: Validation Failed (HTTP 422)\n"
  },
  {
   "action": "thread POST generality",
   "error": "gh: Validation Failed (HTTP 422)\n"
  },
  {
   "action": "thread POST placement",
   "error": "gh: Validation Failed (HTTP 422)\n"
  },
  {
   "action": "thread POST naming",
   "error": "gh: Validation Failed (HTTP 422)\n"
  },
  {
   "action": "thread POST documentation",
   "error": "gh: Validation Failed (HTTP 422)\n"
  },
  {
   "action": "thread POST proof-quality",
   "error": "gh: Validation Failed (HTTP 422)\n"
  },
  {
   "action": "thread POST deprecation",
   "error": "gh: Validation Failed (HTTP 422)\n"
  }
 ],
 "head_sha": "7ea44fd4fe861b4c915f8e3a712a27270337ee85",
 "posted_at": "2026-06-21T12:01:18.013000+00:00",
 "pr": 298,
 "repo": "FormalFrontier/TauCeti",
 "round": 2,
 "schema": "tauceti.post/v1",
 "scoreboard_body_sha256": "f6b7506e99d16205d270c2fc5466bb3abb1c43911d364354a87529cd5223a3b9",
 "scoreboard_comment_id": 4761873367
}
