{
 "head_sha": "8a016ec206808b090297e72c175cd3e7539e9937",
 "posted_at": "2026-06-19T14:53:44.550584+00:00",
 "pr": 222,
 "repo": "FormalFrontier/TauCeti",
 "round": 6,
 "schema": "tauceti.post/v1",
 "scoreboard_body_sha256": "5903eabd733ea40db727fc7407007b40a2f3ef138dc5eeb3849721bc8f54a2cb",
 "scoreboard_comment_id": 4748215537,
 "threads": {
  "deprecation": 3440081290,
  "documentation": 3440081264,
  "generality": 3440081244,
  "naming": 3442835077,
  "placement": 3443069765,
  "scope": 3440081214
 }
}
