{
 "head_sha": "0c2f2b7abdc88d4ca66422381b9d9da288b92772",
 "posted_at": "2026-06-20T21:34:23.774511+00:00",
 "pr": 266,
 "repo": "FormalFrontier/TauCeti",
 "round": 12,
 "schema": "tauceti.post/v1",
 "scoreboard_body_sha256": "29a1e67e31f863aed09fd318c34fae0387daa60053d30476e8109baef5bbccaa",
 "scoreboard_comment_id": 4759362872,
 "threads": {
  "api-design": 3447360516,
  "attribution": 3447360486,
  "correctness": 3447360405,
  "deprecation": 3447360855,
  "documentation": 3447360754,
  "generality": 3447360578,
  "naming": 3447360711,
  "placement": 3447160857,
  "proof-quality": 3447360797,
  "reuse": 3447360425,
  "scope": 3447360453
 }
}
